drpclusters/__init__.py
drpclusters/align_disulfides.py
drpclusters/align_native_overlap.py
drpclusters/cluster_lib.py
drpclusters/cluster_pipeline.py
drpclusters/cluster_vis_annotation.py
drpclusters/pairwise_align.py
drpclusters/salign_tools.py
drpclusters/setup_pdb.py
drpclusters/test/__init__.py
drpclusters/test/test_drp_clusters.py
drpclusters-1.1.1.dist-info/DESCRIPTION.rst
drpclusters-1.1.1.dist-info/METADATA
drpclusters-1.1.1.dist-info/RECORD
drpclusters-1.1.1.dist-info/WHEEL
drpclusters-1.1.1.dist-info/metadata.json
drpclusters-1.1.1.dist-info/top_level.txt
