Metadata-Version: 2.0
Name: drpclusters
Version: 1.1.1
Summary: Structural clustering of disulfide-rich peptides
Home-page: https://github.com/dbarkan/drp-clusters/
Author: Dave Barkan
Author-email: davebarkan@gmail.com
License: GPL
Platform: UNKNOWN
